README.txt
setup.py
docs/HISTORY.txt
docs/INSTALL.txt
docs/LICENSE.GPL
docs/LICENSE.txt
plone/__init__.py
plone.directives.dexterity.egg-info/PKG-INFO
plone.directives.dexterity.egg-info/SOURCES.txt
plone.directives.dexterity.egg-info/dependency_links.txt
plone.directives.dexterity.egg-info/entry_points.txt
plone.directives.dexterity.egg-info/namespace_packages.txt
plone.directives.dexterity.egg-info/not-zip-safe
plone.directives.dexterity.egg-info/requires.txt
plone.directives.dexterity.egg-info/top_level.txt
plone/directives/__init__.py
plone/directives/dexterity/__init__.py
plone/directives/dexterity/configure.zcml
plone/directives/dexterity/content.py
plone/directives/dexterity/form.py
plone/directives/dexterity/meta.zcml
plone/directives/dexterity/tests/__init__.py
plone/directives/dexterity/tests/test_content.py
plone/directives/dexterity/tests/test_form.py