Metadata-Version: 1.0
Name: plone.directives.dexterity
Version: 1.0.1
Summary: Grok-like directives for creating Dexterity content
Home-page: http://code.google.com/p/dexterity
Author: Martin Aspeli
Author-email: optilude@gmail.com
License: LGPL
Keywords: grok plone dexterity content
Platform: UNKNOWN
Classifier: Framework :: Plone
Classifier: Programming Language :: Python
Classifier: Topic :: Software Development :: Libraries :: Python Modules
